calculateForces_benchmark.py
tscw_module/__init__.py
tscw_module/ffmpeg_essentials/bin/ffmpeg.exe
tscw_module/ffmpeg_essentials/doc/bootstrap.min.css
tscw_module/ffmpeg_essentials/doc/community.html
tscw_module/ffmpeg_essentials/doc/default.css
tscw_module/ffmpeg_essentials/doc/developer.html
tscw_module/ffmpeg_essentials/doc/faq.html
tscw_module/ffmpeg_essentials/doc/fate.html
tscw_module/ffmpeg_essentials/doc/ffmpeg-all.html
tscw_module/ffmpeg_essentials/doc/ffmpeg-bitstream-filters.html
tscw_module/ffmpeg_essentials/doc/ffmpeg-codecs.html
tscw_module/ffmpeg_essentials/doc/ffmpeg-devices.html
tscw_module/ffmpeg_essentials/doc/ffmpeg-filters.html
tscw_module/ffmpeg_essentials/doc/ffmpeg-formats.html
tscw_module/ffmpeg_essentials/doc/ffmpeg-protocols.html
tscw_module/ffmpeg_essentials/doc/ffmpeg-resampler.html
tscw_module/ffmpeg_essentials/doc/ffmpeg-scaler.html
tscw_module/ffmpeg_essentials/doc/ffmpeg-utils.html
tscw_module/ffmpeg_essentials/doc/ffmpeg.html
tscw_module/ffmpeg_essentials/doc/ffplay-all.html
tscw_module/ffmpeg_essentials/doc/ffplay.html
tscw_module/ffmpeg_essentials/doc/ffprobe-all.html
tscw_module/ffmpeg_essentials/doc/ffprobe.html
tscw_module/ffmpeg_essentials/doc/general.html
tscw_module/ffmpeg_essentials/doc/git-howto.html
tscw_module/ffmpeg_essentials/doc/libavcodec.html
tscw_module/ffmpeg_essentials/doc/libavdevice.html
tscw_module/ffmpeg_essentials/doc/libavfilter.html
tscw_module/ffmpeg_essentials/doc/libavformat.html
tscw_module/ffmpeg_essentials/doc/libavutil.html
tscw_module/ffmpeg_essentials/doc/libswresample.html
tscw_module/ffmpeg_essentials/doc/libswscale.html
tscw_module/ffmpeg_essentials/doc/mailing-list-faq.html
tscw_module/ffmpeg_essentials/doc/nut.html
tscw_module/ffmpeg_essentials/doc/platform.html
tscw_module/ffmpeg_essentials/doc/style.min.css
tscw_module/ffmpeg_essentials/LICENSE
tscw_module/ffmpeg_essentials/presets/libvpx-1080p.ffpreset
tscw_module/ffmpeg_essentials/presets/libvpx-1080p50_60.ffpreset
tscw_module-1.1.1.dist-info/LICENSE.txt
tscw_module-1.1.1.dist-info/METADATA
tscw_module-1.1.1.dist-info/WHEEL
tscw_module-1.1.1.dist-info/RECORD
